chopt/__init__.py
chopt/__main__.py
chopt/chopt.py
chopt-0.0.6.dist-info/METADATA
chopt-0.0.6.dist-info/RECORD
chopt-0.0.6.dist-info/WHEEL
chopt-0.0.6.dist-info/entry_points.txt
chopt-0.0.6.dist-info/top_level.txt
