Metadata-Version: 2.1
Name: chopt
Version: 0.0.6
Summary: Choose Options using a CLI Checkbox Menu
Home-page: https://github.com/tslight/chopt
Author: Toby Slight
Author-email: tobyslight@gmail.com
License: UNKNOWN
Platform: UNKNOWN
Classifier: Programming Language :: Python :: 3
Classifier: License :: OSI Approved :: ISC License (ISCL)
Classifier: Operating System :: OS Independent
Requires-Dist: columns
